setup.py
SimpleCV/Camera.py
SimpleCV/Color.py
SimpleCV/ColorModel.py
SimpleCV/Display.py
SimpleCV/DrawingLayer.py
SimpleCV/Font.py
SimpleCV/ImageClass.py
SimpleCV/Images.py
SimpleCV/Stream.py
SimpleCV/__init__.py
SimpleCV/base.py
SimpleCV.egg-info/PKG-INFO
SimpleCV.egg-info/SOURCES.txt
SimpleCV.egg-info/dependency_links.txt
SimpleCV.egg-info/top_level.txt
SimpleCV.egg-info/zip-safe
SimpleCV/Features/BOFFeatureExtractor.py
SimpleCV/Features/Blob.py
SimpleCV/Features/BlobMaker.py
SimpleCV/Features/Detection.py
SimpleCV/Features/EdgeHistogramFeatureExtractor.py
SimpleCV/Features/FeatureExtractorBase.py
SimpleCV/Features/Features.py
SimpleCV/Features/HaarLikeFeature.py
SimpleCV/Features/HaarLikeFeatureExtractor.py
SimpleCV/Features/HueHistogramFeatureExtractor.py
SimpleCV/Features/MorphologyFeatureExtractor.py
SimpleCV/Features/__init__.py
SimpleCV/MachineLearning/KNNClassifier.py
SimpleCV/MachineLearning/NaiveBayesClassifier.py
SimpleCV/MachineLearning/SVMClassifier.py
SimpleCV/MachineLearning/TreeClassifier.py
SimpleCV/MachineLearning/__init__.py
SimpleCV/Segmentation/ColorSegmentation.py
SimpleCV/Segmentation/DiffSegmentation.py
SimpleCV/Segmentation/RunningSegmentation.py
SimpleCV/Segmentation/SegmentationBase.py
SimpleCV/Segmentation/__init__.py
SimpleCV/Shell/Cheatsheet.py
SimpleCV/Shell/Example.py
SimpleCV/Shell/Help.py
SimpleCV/Shell/Shell.py
SimpleCV/Shell/Tutorial.py
SimpleCV/Shell/__init__.py
SimpleCV/tests/BOFTester.py
SimpleCV/tests/DisplayTester.py
SimpleCV/tests/MLTestSuite.py
SimpleCV/tests/__init__.py
SimpleCV/tests/test_cameras.py
SimpleCV/tests/test_haar_cascade.py
SimpleCV/tests/tests.py
SimpleCV/tests/vcamera_tests.py